Everything/__init__.py
Everything/eulerhelper.py
eulerhelperpy-0.0.6.dist-info/METADATA
eulerhelperpy-0.0.6.dist-info/WHEEL
eulerhelperpy-0.0.6.dist-info/top_level.txt
eulerhelperpy-0.0.6.dist-info/RECORD
