Metadata-Version: 2.1
Name: eulerhelperpy
Version: 0.0.6
Summary: Helpful Package That Implements Many Different Project Euler Concepts and is a Collection of Project Euler Utilities
Home-page: UNKNOWN
Author: Shaan Cheruvu
Author-email: shaancheruvu@gmail.com
License: UNKNOWN
Keywords: python,euler,project,calculation,math,functions
Platform: UNKNOWN
Classifier: Programming Language :: Python :: 3
Classifier: License :: OSI Approved :: MIT License
Classifier: Operating System :: OS Independent
Requires-Python: >=3.6
